scanbot/App/build/asset-manifest.json
scanbot/App/build/favicon.ico
scanbot/App/build/index.html
scanbot/App/build/manifest.json
scanbot/App/build/static/css/main.fa1115d7.css
scanbot/App/build/static/css/main.fa1115d7.css.map
scanbot/App/build/static/js/main.34356c00.js
scanbot/App/build/static/js/main.34356c00.js.LICENSE.txt
scanbot/App/build/static/js/main.34356c00.js.map
scanbot/App/build/static/media/automation.5a69804e14d581caf24b.png
scanbot/App/build/static/media/back-button.dbc159fe14d62ee6c8fa.png
scanbot/App/build/static/media/bias-dep.8f585512aeae3c340ab3.png
scanbot/App/build/static/media/bias-dep.9e85394bfa0e71bf366e.gif
scanbot/App/build/static/media/config.33b944d6fdbd70a5eaeb.png
scanbot/App/build/static/media/data-acq.63d47148f940fe1d6efd.png
scanbot/App/build/static/media/documentation.e87545e894909a5262ec.png
scanbot/App/build/static/media/frame.a31c6d0e53f2e658cc9f.png
scanbot/App/build/static/media/sts-grid.0800ad76eced278cebc5.png
scanbot/App/build/static/media/sts-grid.4c1bd440ae8bf5ae89b1.gif
scanbot/App/build/static/media/survey.48de6afabfe2873fcb3c.png
scanbot/App/build/static/media/up.9ed6fd33df214c3cd235.png
scanbot/App/public/favicon.ico
scanbot/App/public/index.html
scanbot/App/public/manifest.json
scanbot/App/src/AutoTipShape.js
scanbot/App/src/BiasDep.js
scanbot/App/src/Components.js
scanbot/App/src/Configuration.js
scanbot/App/src/DataAcquisition.js
scanbot/App/src/img/automation.png
scanbot/App/src/img/back-button.png
scanbot/App/src/img/bias-dep.gif
scanbot/App/src/img/bias-dep.png
scanbot/App/src/img/coming-soon.png
scanbot/App/src/img/config.png
scanbot/App/src/img/data-acq.png
scanbot/App/src/img/documentation.png
scanbot/App/src/img/frame-wide.png
scanbot/App/src/img/frame.png
scanbot/App/src/img/sts-grid.gif
scanbot/App/src/img/sts-grid.png
scanbot/App/src/img/survey.png
scanbot/App/src/img/up.png
scanbot/App/src/index.js
scanbot/App/src/QuickAccess.js
scanbot/App/src/Scanbot.js
scanbot/App/src/STMControl.js
scanbot-4.5.1.dist-info/entry_points.txt
scanbot-4.5.1.dist-info/LICENSE
scanbot-4.5.1.dist-info/METADATA
scanbot-4.5.1.dist-info/WHEEL
scanbot-4.5.1.dist-info/RECORD
