Metadata-Version: 2.1
Name: scanbot
Version: 4.5.1
Summary: Collection of automated STM and nc-AFM commands compatible with Nanonis V5 SPM Controller
License: MIT
Keywords: stm,automation,python,scanning tunnelling microscopy,sts,scanbot
Author: Julian Ceddia
Author-email: jdceddia@gmail.com
Requires-Python: >=3.9,<4.0
Classifier: License :: OSI Approved :: MIT License
Classifier: Programming Language :: Python :: 3
Classifier: Programming Language :: Python :: 3.9
Classifier: Programming Language :: Python :: 3.10
Classifier: Programming Language :: Python :: 3.11
Classifier: Programming Language :: Python :: 3.12
Requires-Dist: flask
Requires-Dist: flask-cors
Requires-Dist: matplotlib
Requires-Dist: nanonisTCP (>1.1.1)
Requires-Dist: numpy (<2)
Requires-Dist: opencv-python (<4.9.0.81)
Requires-Dist: panel
Requires-Dist: pytest
Requires-Dist: scipy (<1.14)
Requires-Dist: zulip
